sitemaker
sitemaker/themes
