Metadata-Version: 2.1
Name: sitemaker
Version: 0.4.1
Summary: A site maker
Home-page: https://gitlab.com/sulincix/sitemaker
Author: sulincix
Author-email: aa@aa.aa
License: UNKNOWN
Platform: UNKNOWN
